{
  "formatVersion": 1,
  "database": {
    "version": 2,
    "identityHash": "17d7efe546c20e5b3abd002b57ba2987",
    "entities": [
      {
        "tableName": "IngredientRoom",
        "createSql": "CREATE TABLE IF NOT EXISTS `${TABLE_NAME}` (`ingredientCategoryId` INTEGER NOT NULL, `img` TEXT NOT NULL, `name` TEXT NOT NULL, `measure` TEXT NOT NULL, `ingredientId` INTEGER PRIMARY KEY AUTOINCREMENT NOT NULL)",
        "fields": [
          {
            "fieldPath": "ingredientCategoryId",
            "columnName": "ingredientCategoryId",
            "affinity": "INTEGER",
            "notNull": true
          },
          {
            "fieldPath": "img",
            "columnName": "img",
            "affinity": "TEXT",
            "notNull": true
          },
          {
            "fieldPath": "name",
            "columnName": "name",
            "affinity": "TEXT",
            "notNull": true
          },
          {
            "fieldPath": "measure",
            "columnName": "measure",
            "affinity": "TEXT",
            "notNull": true
          },
          {
            "fieldPath": "ingredientId",
            "columnName": "ingredientId",
            "affinity": "INTEGER",
            "notNull": true
          }
        ],
        "primaryKey": {
          "autoGenerate": true,
          "columnNames": [
            "ingredientId"
          ]
        },
        "indices": [],
        "foreignKeys": []
      },
      {
        "tableName": "IngredientCategoryRoom",
        "createSql": "CREATE TABLE IF NOT EXISTS `${TABLE_NAME}` (`name` TEXT NOT NULL, `ingredientCategoryId` INTEGER PRIMARY KEY AUTOINCREMENT NOT NULL)",
        "fields": [
          {
            "fieldPath": "name",
            "columnName": "name",
            "affinity": "TEXT",
            "notNull": true
          },
          {
            "fieldPath": "ingredientCategoryId",
            "columnName": "ingredientCategoryId",
            "affinity": "INTEGER",
            "notNull": true
          }
        ],
        "primaryKey": {
          "autoGenerate": true,
          "columnNames": [
            "ingredientCategoryId"
          ]
        },
        "indices": [],
        "foreignKeys": []
      },
      {
        "tableName": "IngredientInRecipeRoom",
        "createSql": "CREATE TABLE IF NOT EXISTS `${TABLE_NAME}` (`recipeId` INTEGER NOT NULL, `ingredientId` INTEGER NOT NULL, `description` TEXT NOT NULL, `count` REAL NOT NULL, `id` INTEGER PRIMARY KEY AUTOINCREMENT NOT NULL)",
        "fields": [
          {
            "fieldPath": "recipeId",
            "columnName": "recipeId",
            "affinity": "INTEGER",
            "notNull": true
          },
          {
            "fieldPath": "ingredientId",
            "columnName": "ingredientId",
            "affinity": "INTEGER",
            "notNull": true
          },
          {
            "fieldPath": "description",
            "columnName": "description",
            "affinity": "TEXT",
            "notNull": true
          },
          {
            "fieldPath": "count",
            "columnName": "count",
            "affinity": "REAL",
            "notNull": true
          },
          {
            "fieldPath": "id",
            "columnName": "id",
            "affinity": "INTEGER",
            "notNull": true
          }
        ],
        "primaryKey": {
          "autoGenerate": true,
          "columnNames": [
            "id"
          ]
        },
        "indices": [],
        "foreignKeys": []
      },
      {
        "tableName": "RecipeRoom",
        "createSql": "CREATE TABLE IF NOT EXISTS `${TABLE_NAME}` (`name` TEXT NOT NULL, `description` TEXT NOT NULL, `img` TEXT NOT NULL, `standardPortionsCount` INTEGER NOT NULL, `link` TEXT NOT NULL, `inFavorite` INTEGER NOT NULL, `lastEdit` TEXT NOT NULL, `duration` TEXT NOT NULL, `recipeId` INTEGER PRIMARY KEY AUTOINCREMENT NOT NULL)",
        "fields": [
          {
            "fieldPath": "name",
            "columnName": "name",
            "affinity": "TEXT",
            "notNull": true
          },
          {
            "fieldPath": "description",
            "columnName": "description",
            "affinity": "TEXT",
            "notNull": true
          },
          {
            "fieldPath": "img",
            "columnName": "img",
            "affinity": "TEXT",
            "notNull": true
          },
          {
            "fieldPath": "standardPortionsCount",
            "columnName": "standardPortionsCount",
            "affinity": "INTEGER",
            "notNull": true
          },
          {
            "fieldPath": "link",
            "columnName": "link",
            "affinity": "TEXT",
            "notNull": true
          },
          {
            "fieldPath": "inFavorite",
            "columnName": "inFavorite",
            "affinity": "INTEGER",
            "notNull": true
          },
          {
            "fieldPath": "lastEdit",
            "columnName": "lastEdit",
            "affinity": "TEXT",
            "notNull": true
          },
          {
            "fieldPath": "duration",
            "columnName": "duration",
            "affinity": "TEXT",
            "notNull": true
          },
          {
            "fieldPath": "recipeId",
            "columnName": "recipeId",
            "affinity": "INTEGER",
            "notNull": true
          }
        ],
        "primaryKey": {
          "autoGenerate": true,
          "columnNames": [
            "recipeId"
          ]
        },
        "indices": [],
        "foreignKeys": []
      },
      {
        "tableName": "RecipeRecipeTagCrossRef",
        "createSql": "CREATE TABLE IF NOT EXISTS `${TABLE_NAME}` (`recipeId` INTEGER NOT NULL, `recipeTagId` INTEGER NOT NULL, PRIMARY KEY(`recipeId`, `recipeTagId`))",
        "fields": [
          {
            "fieldPath": "recipeId",
            "columnName": "recipeId",
            "affinity": "INTEGER",
            "notNull": true
          },
          {
            "fieldPath": "recipeTagId",
            "columnName": "recipeTagId",
            "affinity": "INTEGER",
            "notNull": true
          }
        ],
        "primaryKey": {
          "autoGenerate": false,
          "columnNames": [
            "recipeId",
            "recipeTagId"
          ]
        },
        "indices": [],
        "foreignKeys": []
      },
      {
        "tableName": "RecipeStepRoom",
        "createSql": "CREATE TABLE IF NOT EXISTS `${TABLE_NAME}` (`recipeId` INTEGER NOT NULL, `description` TEXT NOT NULL, `image` TEXT NOT NULL, `timer` INTEGER NOT NULL, `ingredientsPinned` TEXT NOT NULL, `id` INTEGER PRIMARY KEY AUTOINCREMENT NOT NULL)",
        "fields": [
          {
            "fieldPath": "recipeId",
            "columnName": "recipeId",
            "affinity": "INTEGER",
            "notNull": true
          },
          {
            "fieldPath": "description",
            "columnName": "description",
            "affinity": "TEXT",
            "notNull": true
          },
          {
            "fieldPath": "image",
            "columnName": "image",
            "affinity": "TEXT",
            "notNull": true
          },
          {
            "fieldPath": "timer",
            "columnName": "timer",
            "affinity": "INTEGER",
            "notNull": true
          },
          {
            "fieldPath": "ingredientsPinned",
            "columnName": "ingredientsPinned",
            "affinity": "TEXT",
            "notNull": true
          },
          {
            "fieldPath": "id",
            "columnName": "id",
            "affinity": "INTEGER",
            "notNull": true
          }
        ],
        "primaryKey": {
          "autoGenerate": true,
          "columnNames": [
            "id"
          ]
        },
        "indices": [],
        "foreignKeys": []
      },
      {
        "tableName": "RecipeTagRoom",
        "createSql": "CREATE TABLE IF NOT EXISTS `${TABLE_NAME}` (`recipeTagCategoryId` INTEGER NOT NULL, `tagName` TEXT NOT NULL, `recipeTagId` INTEGER PRIMARY KEY AUTOINCREMENT NOT NULL)",
        "fields": [
          {
            "fieldPath": "recipeTagCategoryId",
            "columnName": "recipeTagCategoryId",
            "affinity": "INTEGER",
            "notNull": true
          },
          {
            "fieldPath": "tagName",
            "columnName": "tagName",
            "affinity": "TEXT",
            "notNull": true
          },
          {
            "fieldPath": "recipeTagId",
            "columnName": "recipeTagId",
            "affinity": "INTEGER",
            "notNull": true
          }
        ],
        "primaryKey": {
          "autoGenerate": true,
          "columnNames": [
            "recipeTagId"
          ]
        },
        "indices": [],
        "foreignKeys": []
      },
      {
        "tableName": "RecipeTagCategoryRoom",
        "createSql": "CREATE TABLE IF NOT EXISTS `${TABLE_NAME}` (`name` TEXT NOT NULL, `recipeTagCategoryId` INTEGER PRIMARY KEY AUTOINCREMENT NOT NULL)",
        "fields": [
          {
            "fieldPath": "name",
            "columnName": "name",
            "affinity": "TEXT",
            "notNull": true
          },
          {
            "fieldPath": "recipeTagCategoryId",
            "columnName": "recipeTagCategoryId",
            "affinity": "INTEGER",
            "notNull": true
          }
        ],
        "primaryKey": {
          "autoGenerate": true,
          "columnNames": [
            "recipeTagCategoryId"
          ]
        },
        "indices": [],
        "foreignKeys": []
      },
      {
        "tableName": "PositionRecipeRoom",
        "createSql": "CREATE TABLE IF NOT EXISTS `${TABLE_NAME}` (`recipeId` INTEGER NOT NULL, `portionsCount` INTEGER NOT NULL, `selectionId` INTEGER NOT NULL, `recipeInMenuId` INTEGER PRIMARY KEY AUTOINCREMENT NOT NULL)",
        "fields": [
          {
            "fieldPath": "recipeId",
            "columnName": "recipeId",
            "affinity": "INTEGER",
            "notNull": true
          },
          {
            "fieldPath": "portionsCount",
            "columnName": "portionsCount",
            "affinity": "INTEGER",
            "notNull": true
          },
          {
            "fieldPath": "selectionId",
            "columnName": "selectionId",
            "affinity": "INTEGER",
            "notNull": true
          },
          {
            "fieldPath": "recipeInMenuId",
            "columnName": "recipeInMenuId",
            "affinity": "INTEGER",
            "notNull": true
          }
        ],
        "primaryKey": {
          "autoGenerate": true,
          "columnNames": [
            "recipeInMenuId"
          ]
        },
        "indices": [],
        "foreignKeys": []
      },
      {
        "tableName": "SelectionRoom",
        "createSql": "CREATE TABLE IF NOT EXISTS `${TABLE_NAME}` (`name` TEXT NOT NULL, `dateTime` TEXT NOT NULL, `weekOfYear` INTEGER NOT NULL, `isForWeek` INTEGER NOT NULL, `test` INTEGER NOT NULL DEFAULT false, `id` INTEGER PRIMARY KEY AUTOINCREMENT NOT NULL)",
        "fields": [
          {
            "fieldPath": "name",
            "columnName": "name",
            "affinity": "TEXT",
            "notNull": true
          },
          {
            "fieldPath": "dateTime",
            "columnName": "dateTime",
            "affinity": "TEXT",
            "notNull": true
          },
          {
            "fieldPath": "weekOfYear",
            "columnName": "weekOfYear",
            "affinity": "INTEGER",
            "notNull": true
          },
          {
            "fieldPath": "isForWeek",
            "columnName": "isForWeek",
            "affinity": "INTEGER",
            "notNull": true
          },
          {
            "fieldPath": "test",
            "columnName": "test",
            "affinity": "INTEGER",
            "notNull": true,
            "defaultValue": "false"
          },
          {
            "fieldPath": "id",
            "columnName": "id",
            "affinity": "INTEGER",
            "notNull": true
          }
        ],
        "primaryKey": {
          "autoGenerate": true,
          "columnNames": [
            "id"
          ]
        },
        "indices": [],
        "foreignKeys": []
      },
      {
        "tableName": "PositionIngredientRoom",
        "createSql": "CREATE TABLE IF NOT EXISTS `${TABLE_NAME}` (`ingredientInRecipeId` INTEGER NOT NULL, `selectionId` INTEGER NOT NULL, `positionIngredientId` INTEGER PRIMARY KEY AUTOINCREMENT NOT NULL)",
        "fields": [
          {
            "fieldPath": "ingredientInRecipeId",
            "columnName": "ingredientInRecipeId",
            "affinity": "INTEGER",
            "notNull": true
          },
          {
            "fieldPath": "selectionId",
            "columnName": "selectionId",
            "affinity": "INTEGER",
            "notNull": true
          },
          {
            "fieldPath": "positionIngredientId",
            "columnName": "positionIngredientId",
            "affinity": "INTEGER",
            "notNull": true
          }
        ],
        "primaryKey": {
          "autoGenerate": true,
          "columnNames": [
            "positionIngredientId"
          ]
        },
        "indices": [],
        "foreignKeys": []
      },
      {
        "tableName": "PositionNoteRoom",
        "createSql": "CREATE TABLE IF NOT EXISTS `${TABLE_NAME}` (`note` TEXT NOT NULL, `selectionId` INTEGER NOT NULL, `id` INTEGER PRIMARY KEY AUTOINCREMENT NOT NULL)",
        "fields": [
          {
            "fieldPath": "note",
            "columnName": "note",
            "affinity": "TEXT",
            "notNull": true
          },
          {
            "fieldPath": "selectionId",
            "columnName": "selectionId",
            "affinity": "INTEGER",
            "notNull": true
          },
          {
            "fieldPath": "id",
            "columnName": "id",
            "affinity": "INTEGER",
            "notNull": true
          }
        ],
        "primaryKey": {
          "autoGenerate": true,
          "columnNames": [
            "id"
          ]
        },
        "indices": [],
        "foreignKeys": []
      },
      {
        "tableName": "PositionDraftRoom",
        "createSql": "CREATE TABLE IF NOT EXISTS `${TABLE_NAME}` (`selectionId` INTEGER NOT NULL, `draftId` INTEGER PRIMARY KEY AUTOINCREMENT NOT NULL)",
        "fields": [
          {
            "fieldPath": "selectionId",
            "columnName": "selectionId",
            "affinity": "INTEGER",
            "notNull": true
          },
          {
            "fieldPath": "draftId",
            "columnName": "draftId",
            "affinity": "INTEGER",
            "notNull": true
          }
        ],
        "primaryKey": {
          "autoGenerate": true,
          "columnNames": [
            "draftId"
          ]
        },
        "indices": [],
        "foreignKeys": []
      },
      {
        "tableName": "DraftAndIngredientCrossRef",
        "createSql": "CREATE TABLE IF NOT EXISTS `${TABLE_NAME}` (`draftId` INTEGER NOT NULL, `ingredientId` INTEGER NOT NULL, PRIMARY KEY(`draftId`, `ingredientId`))",
        "fields": [
          {
            "fieldPath": "draftId",
            "columnName": "draftId",
            "affinity": "INTEGER",
            "notNull": true
          },
          {
            "fieldPath": "ingredientId",
            "columnName": "ingredientId",
            "affinity": "INTEGER",
            "notNull": true
          }
        ],
        "primaryKey": {
          "autoGenerate": false,
          "columnNames": [
            "draftId",
            "ingredientId"
          ]
        },
        "indices": [],
        "foreignKeys": []
      },
      {
        "tableName": "DraftAndTagCrossRef",
        "createSql": "CREATE TABLE IF NOT EXISTS `${TABLE_NAME}` (`draftId` INTEGER NOT NULL, `recipeTagId` INTEGER NOT NULL, PRIMARY KEY(`draftId`, `recipeTagId`))",
        "fields": [
          {
            "fieldPath": "draftId",
            "columnName": "draftId",
            "affinity": "INTEGER",
            "notNull": true
          },
          {
            "fieldPath": "recipeTagId",
            "columnName": "recipeTagId",
            "affinity": "INTEGER",
            "notNull": true
          }
        ],
        "primaryKey": {
          "autoGenerate": false,
          "columnNames": [
            "draftId",
            "recipeTagId"
          ]
        },
        "indices": [],
        "foreignKeys": []
      },
      {
        "tableName": "ShoppingItemRoom",
        "createSql": "CREATE TABLE IF NOT EXISTS `${TABLE_NAME}` (`ingredientInRecipeId` INTEGER NOT NULL, `checked` INTEGER NOT NULL, `id` INTEGER PRIMARY KEY AUTOINCREMENT NOT NULL)",
        "fields": [
          {
            "fieldPath": "ingredientInRecipeId",
            "columnName": "ingredientInRecipeId",
            "affinity": "INTEGER",
            "notNull": true
          },
          {
            "fieldPath": "checked",
            "columnName": "checked",
            "affinity": "INTEGER",
            "notNull": true
          },
          {
            "fieldPath": "id",
            "columnName": "id",
            "affinity": "INTEGER",
            "notNull": true
          }
        ],
        "primaryKey": {
          "autoGenerate": true,
          "columnNames": [
            "id"
          ]
        },
        "indices": [],
        "foreignKeys": []
      },
      {
        "tableName": "CookPlannerStepRoom",
        "createSql": "CREATE TABLE IF NOT EXISTS `${TABLE_NAME}` (`plannerGroupId` INTEGER NOT NULL, `originalStepId` INTEGER NOT NULL, `checked` INTEGER NOT NULL, `id` INTEGER PRIMARY KEY AUTOINCREMENT NOT NULL)",
        "fields": [
          {
            "fieldPath": "plannerGroupId",
            "columnName": "plannerGroupId",
            "affinity": "INTEGER",
            "notNull": true
          },
          {
            "fieldPath": "originalStepId",
            "columnName": "originalStepId",
            "affinity": "INTEGER",
            "notNull": true
          },
          {
            "fieldPath": "checked",
            "columnName": "checked",
            "affinity": "INTEGER",
            "notNull": true
          },
          {
            "fieldPath": "id",
            "columnName": "id",
            "affinity": "INTEGER",
            "notNull": true
          }
        ],
        "primaryKey": {
          "autoGenerate": true,
          "columnNames": [
            "id"
          ]
        },
        "indices": [],
        "foreignKeys": []
      },
      {
        "tableName": "CookPlannerGroupRoom",
        "createSql": "CREATE TABLE IF NOT EXISTS `${TABLE_NAME}` (`recipeId` INTEGER NOT NULL, `portionsCount` INTEGER NOT NULL, `start` TEXT NOT NULL, `id` INTEGER PRIMARY KEY AUTOINCREMENT NOT NULL)",
        "fields": [
          {
            "fieldPath": "recipeId",
            "columnName": "recipeId",
            "affinity": "INTEGER",
            "notNull": true
          },
          {
            "fieldPath": "portionsCount",
            "columnName": "portionsCount",
            "affinity": "INTEGER",
            "notNull": true
          },
          {
            "fieldPath": "start",
            "columnName": "start",
            "affinity": "TEXT",
            "notNull": true
          },
          {
            "fieldPath": "id",
            "columnName": "id",
            "affinity": "INTEGER",
            "notNull": true
          }
        ],
        "primaryKey": {
          "autoGenerate": true,
          "columnNames": [
            "id"
          ]
        },
        "indices": [],
        "foreignKeys": []
      },
      {
        "tableName": "CategorySelectionRoom",
        "createSql": "CREATE TABLE IF NOT EXISTS `${TABLE_NAME}` (`name` TEXT NOT NULL, `stdTime` TEXT NOT NULL, `id` INTEGER PRIMARY KEY AUTOINCREMENT NOT NULL)",
        "fields": [
          {
            "fieldPath": "name",
            "columnName": "name",
            "affinity": "TEXT",
            "notNull": true
          },
          {
            "fieldPath": "stdTime",
            "columnName": "stdTime",
            "affinity": "TEXT",
            "notNull": true
          },
          {
            "fieldPath": "id",
            "columnName": "id",
            "affinity": "INTEGER",
            "notNull": true
          }
        ],
        "primaryKey": {
          "autoGenerate": true,
          "columnNames": [
            "id"
          ]
        },
        "indices": [],
        "foreignKeys": []
      }
    ],
    "views": [],
    "setupQueries": [
      "CREATE TABLE IF NOT EXISTS room_master_table (id INTEGER PRIMARY KEY,identity_hash TEXT)",
      "INSERT OR REPLACE INTO room_master_table (id,identity_hash) VALUES(42, '17d7efe546c20e5b3abd002b57ba2987')"
    ]
  }
}